cbs_hist_downloader/__init__.py
cbs_hist_downloader/find_next_page.py
cbs_hist_downloader/scrape_book.py
cbs_hist_downloader-1.0.2.dist-info/LICENSE
cbs_hist_downloader-1.0.2.dist-info/METADATA
cbs_hist_downloader-1.0.2.dist-info/WHEEL
cbs_hist_downloader-1.0.2.dist-info/top_level.txt
cbs_hist_downloader-1.0.2.dist-info/RECORD
