Metadata-Version: 2.1
Name: cbs-hist-downloader
Version: 1.0.2
Summary: A python program for downloading images from CBS historisch.
Home-page: https://github.com/basm92/cbs_hist_downloader
Author: Bas Machieslen
Author-email: basmachielsen@live.nl
Project-URL: Bug Tracker, https://github.com/basm92/cbs_hist_downloader/issues
Classifier: Programming Language :: Python :: 3
Classifier: License :: OSI Approved :: MIT License
Classifier: Operating System :: OS Independent
Requires-Python: >=3.6
License-File: LICENSE
Requires-Dist: selenium
Requires-Dist: webdriver-manager
